cf_recommender
