Metadata-Version: 1.1
Name: cf-recommender
Version: 1.0.1
Summary: Real Time Recommendation System of Collaborative Filtering
Home-page: https://github.com/subc/cf_recommender
Author: haminiku
Author-email: haminiku1129@gmail.com
License: MIT License
Keywords: recommendation,recommender,cf,Collaborative,Collaborative Filtering
Platform: UNKNOWN
Classifier: License :: Free For Home Use
Classifier: Programming Language :: Python
Classifier: Programming Language :: Python :: 2.6
Classifier: Programming Language :: Python :: 2.7
Classifier: Programming Language :: Python :: 3
Classifier: Programming Language :: Python :: 3.3
Classifier: Programming Language :: Python :: 3.4
